joblet_mcp_server/__init__.py
joblet_mcp_server/server.py
joblet_mcp_server/server_sdk.py
joblet_mcp_server-1.1.3.dist-info/licenses/LICENSE
joblet_mcp_server-1.1.3.dist-info/METADATA
joblet_mcp_server-1.1.3.dist-info/WHEEL
joblet_mcp_server-1.1.3.dist-info/entry_points.txt
joblet_mcp_server-1.1.3.dist-info/top_level.txt
joblet_mcp_server-1.1.3.dist-info/RECORD
