Metadata-Version: 2.4
Name: joblet-mcp-server
Version: 1.1.3
Summary: MCP (Model Context Protocol) server for Joblet job orchestration system
Author: Jay Ehsaniara
License: MIT
Project-URL: Homepage, https://github.com/ehsaniara/joblet-mcp-server
Project-URL: Repository, https://github.com/ehsaniara/joblet-mcp-server
Project-URL: Documentation, https://github.com/ehsaniara/joblet-mcp-server/blob/main/README.md
Classifier: Development Status :: 4 - Beta
Classifier: Intended Audience :: Developers
Classifier: License :: OSI Approved :: MIT License
Classifier: Programming Language :: Python :: 3
Classifier: Programming Language :: Python :: 3.10
Classifier: Programming Language :: Python :: 3.11
Classifier: Programming Language :: Python :: 3.12
Classifier: Topic :: Software Development :: Libraries :: Python Modules
Classifier: Topic :: System :: Distributed Computing
Requires-Python: >=3.10
License-File: LICENSE
Requires-Dist: mcp>=1.0.0
Requires-Dist: pydantic>=2.0.0
Requires-Dist: typing-extensions>=4.8.0
Requires-Dist: aiofiles>=23.0.0
Provides-Extra: sdk
Requires-Dist: joblet-sdk-python>=2.1.1; extra == "sdk"
Provides-Extra: cli
Provides-Extra: dev
Requires-Dist: pytest>=7.0.0; extra == "dev"
Requires-Dist: pytest-asyncio>=0.21.0; extra == "dev"
Requires-Dist: pytest-cov>=4.0.0; extra == "dev"
Requires-Dist: black>=23.0.0; extra == "dev"
Requires-Dist: isort>=5.12.0; extra == "dev"
Requires-Dist: mypy>=1.5.0; extra == "dev"
Requires-Dist: flake8>=6.0.0; extra == "dev"
Requires-Dist: pre-commit>=3.0.0; extra == "dev"
Dynamic: license-file
